toca/__init__.py
toca/cmd.py
toca/index.py
toca/main.py
toca/entity/__init__.py
toca/entity/api.py
toca/entity/group.py
toca/entity/root.py
toca/entity/service.py
toca/utils/errors.py
toca/utils/functions.py
toca/utils/log.py
toca/utils/parse.py
toca-0.3.6.dist-info/LICENSE
toca-0.3.6.dist-info/METADATA
toca-0.3.6.dist-info/WHEEL
toca-0.3.6.dist-info/entry_points.txt
toca-0.3.6.dist-info/top_level.txt
toca-0.3.6.dist-info/RECORD
