Metadata-Version: 2.1
Name: toca
Version: 0.3.6
Summary: Automatic Testing
Home-page: https://gitee.com/olivetree123/toca
Author: Gaojian
Author-email: olivetree123@163.com
License: MIT
Platform: UNKNOWN
License-File: LICENSE
Requires-Dist: Jinja2
Requires-Dist: chardet
Requires-Dist: toml
Requires-Dist: click
Requires-Dist: winney (>=0.5.6)
